Metadata-Version: 2.1
Name: nepspell-datautils
Version: 0.1.0
Summary: Utility for spelling error correction synthetic data generation.
Home-page: UNKNOWN
Author: dura-garage
Author-email: duragarage0@gmail.com
License: UNKNOWN
Platform: UNKNOWN
Classifier: Programming Language :: Python :: 3
Classifier: License :: OSI Approved :: MIT License
Classifier: Operating System :: OS Independent
Requires-Python: >=3.6
